{
  "reference_period": "2024-01",
  "fetched_at": "2026-01-23T23:47:07.451Z",
  "metrics": {
    "payrolls": {
      "raw_value": 157049,
      "display_value": 157049,
      "unit": "thousands",
      "scale": 1,
      "precision": 0
    },
    "unemployment": {
      "raw_value": 3.7,
      "display_value": 3.7,
      "unit": "number",
      "scale": 1,
      "precision": 2
    },
    "wages": {
      "raw_value": 34.47,
      "display_value": 34.47,
      "unit": "number",
      "scale": 1,
      "precision": 2
    }
  },
  "deltas": {},
  "comparisons": {
    "prior_release": {},
    "twelve_month_average": {
      "payrolls": 157049,
      "unemployment": 3.7,
      "wages": 34.47
    },
    "trend": {
      "payrolls": [
        null,
        null,
        null,
        null,
        null,
        null,
        null,
        null,
        null,
        null,
        null,
        null,
        null,
        null,
        null,
        null,
        null,
        null,
        null,
        null,
        null,
        null,
        null,
        157049
      ],
      "unemployment": [
        null,
        null,
        null,
        null,
        null,
        null,
        null,
        null,
        null,
        null,
        null,
        null,
        null,
        null,
        null,
        null,
        null,
        null,
        null,
        null,
        null,
        null,
        null,
        3.7
      ],
      "wages": [
        null,
        null,
        null,
        null,
        null,
        null,
        null,
        null,
        null,
        null,
        null,
        null,
        null,
        null,
        null,
        null,
        null,
        null,
        null,
        null,
        null,
        null,
        null,
        34.47
      ]
    }
  }
}